AUTHORS.rst
CONTRIBUTING.rst
HISTORY.rst
LICENSE
MANIFEST.in
README.rst
setup.cfg
setup.py
docker_links/__init__.py
docker_links/internals.py
docker_links.egg-info/PKG-INFO
docker_links.egg-info/SOURCES.txt
docker_links.egg-info/dependency_links.txt
docker_links.egg-info/not-zip-safe
docker_links.egg-info/top_level.txt
docs/Makefile
docs/authors.rst
docs/conf.py
docs/contributing.rst
docs/history.rst
docs/index.rst
docs/installation.rst
docs/make.bat
docs/readme.rst
docs/usage.rst
tests/__init__.py
tests/test_docker_links.py