Metadata-Version: 1.1
Name: docker-links
Version: 0.1.0
Summary: Parse Docker links into values useful for Django settings.
Home-page: https://github.com/wlonk/docker_links
Author: Kit La Touche
Author-email: kit@transneptune.net
License: BSD
Keywords: docker_links
Platform: UNKNOWN
Classifier: Development Status :: 3 - Alpha
Classifier: Intended Audience :: Developers
Classifier: License :: OSI Approved :: BSD License
Classifier: Natural Language :: English
Classifier: Programming Language :: Python :: 2
Classifier: Programming Language :: Python :: 2.7
Classifier: Intended Audience :: Developers
